python_snaptime/__init__.py
python_snaptime/__version__.py
python_snaptime/handlers.py
python_snaptime/main.py
python_snaptime/models.py
python_snaptime/parsers.py
python_snaptime/py.typed
python_snaptime-0.1.2.dist-info/LICENSE
python_snaptime-0.1.2.dist-info/METADATA
python_snaptime-0.1.2.dist-info/WHEEL
python_snaptime-0.1.2.dist-info/RECORD
