Metadata-Version: 2.1
Name: python-snaptime
Version: 0.1.2
Summary: Easily manipulate datetime objects with relative time modifiers. Snap, shift, and chain operations on timezone-aware datetimes. E.g `@d-2h`
Home-page: https://github.com/dtomlinson91/python-snaptime
License: ISC
Keywords: datetime,time,datetime,timesnap,timesnapper,snaptime 
Author: Daniel Tomlinson
Author-email: dtomlinson@panaetius.co.uk
Requires-Python: >=3.9,<4.0
Classifier: License :: OSI Approved
Classifier: Programming Language :: Python :: 3
Classifier: Programming Language :: Python :: 3.9
Classifier: Programming Language :: Python :: 3.10
Classifier: Programming Language :: Python :: 3.11
Requires-Dist: eval-type-backport (>=0.2.2,<0.3.0)
Requires-Dist: pendulum (>=3.0.0,<4.0.0)
Requires-Dist: pydantic (>=2.10.4,<3.0.0)
Project-URL: Documentation, https://github.com/dtomlinson91/python-snaptime
Project-URL: Repository, https://github.com/dtomlinson91/python-snaptime
